.clang-format
.flake8
.gitignore
.gitmodules
CHANGELOG.md
CODEOWNERS
CODE_OF_CONDUCT
Dockerfile
Dockerfile-cuda
Dockerfile-embedded
LICENSE
MANIFEST.in
Makefile
README.md
__init__.py
description.txt
packages.txt
setup.py
./src/opendr/__init__.py
./src/opendr/_setup.py
./src/opendr/_version.py
./src/opendr/control/__init__.py
./src/opendr/engine/__init__.py
./src/opendr/engine/constants.py
./src/opendr/engine/data.py
./src/opendr/engine/datasets.py
./src/opendr/engine/example_learner.py
./src/opendr/engine/learners.py
./src/opendr/engine/target.py
./src/opendr/perception/__init__.py
./src/opendr/perception/object_detection_3d/__init__.py
./src/opendr/perception/object_detection_3d/datasets/__init__.py
./src/opendr/perception/object_detection_3d/datasets/create_data_kitti.py
./src/opendr/perception/object_detection_3d/datasets/kitti.py
./src/opendr/perception/object_detection_3d/datasets/kitti_subsets/test.txt
./src/opendr/perception/object_detection_3d/datasets/kitti_subsets/train.txt
./src/opendr/perception/object_detection_3d/datasets/kitti_subsets/val.txt
./src/opendr/perception/object_detection_3d/datasets/mini_kitti_subsets/test.txt
./src/opendr/perception/object_detection_3d/datasets/mini_kitti_subsets/train.txt
./src/opendr/perception/object_detection_3d/datasets/mini_kitti_subsets/val.txt
./src/opendr/perception/object_detection_3d/datasets/nano_kitti_subsets/test.txt
./src/opendr/perception/object_detection_3d/datasets/nano_kitti_subsets/train.txt
./src/opendr/perception/object_detection_3d/datasets/nano_kitti_subsets/val.txt
./src/opendr/perception/object_detection_3d/voxel_object_detection_3d/.gitignore
./src/opendr/perception/object_detection_3d/voxel_object_detection_3d/README.md
./src/opendr/perception/object_detection_3d/voxel_object_detection_3d/__init__.py
./src/opendr/perception/object_detection_3d/voxel_object_detection_3d/dependencies.ini
./src/opendr/perception/object_detection_3d/voxel_object_detection_3d/logger.py
./src/opendr_toolkit_object_detection_3d.egg-info/PKG-INFO
./src/opendr_toolkit_object_detection_3d.egg-info/SOURCES.txt
./src/opendr_toolkit_object_detection_3d.egg-info/dependency_links.txt
./src/opendr_toolkit_object_detection_3d.egg-info/requires.txt
./src/opendr_toolkit_object_detection_3d.egg-info/top_level.txt
